youdao_simple/__init__.py
youdao_simple/youdao.py
youdao_simple-1.1.0.dist-info/DESCRIPTION.rst
youdao_simple-1.1.0.dist-info/METADATA
youdao_simple-1.1.0.dist-info/RECORD
youdao_simple-1.1.0.dist-info/WHEEL
youdao_simple-1.1.0.dist-info/entry_points.txt
youdao_simple-1.1.0.dist-info/metadata.json
youdao_simple-1.1.0.dist-info/top_level.txt
