Metadata-Version: 2.0
Name: youdao-simple
Version: 1.1.0
Summary: Youdao Python
Home-page: https://github.com/mudongliang/youdao-python
Author: Dongliang Mu
Author-email: mudongliangabcd@gmail.com
License: GPL v3.0
Platform: UNKNOWN
Classifier: License :: OSI Approved :: GNU General Public License v3 (GPLv3)
Classifier: Programming Language :: Python :: 2
Classifier: Programming Language :: Python :: 3
